csputils-0.1.1.dist-info/RECORD
csputils-0.1.1.dist-info/top_level.txt
csputils-0.1.1.dist-info/WHEEL
csputils-0.1.1.dist-info/METADATA
csputils-0.1.1.dist-info/DESCRIPTION.rst
csputils-0.1.1.dist-info/metadata.json
csputils/test_csp.py
csputils/csp.py
csputils/__init__.py
