Metadata-Version: 2.0
Name: csputils
Version: 0.1.1
Summary: csputils - helpers for writing Content-Security-Policy rules
Home-page: https://github.com/jamesbroadhead/csputils.git
Author: jbroadhead
Author-email: jbroadhead@twitter.com
License: UNKNOWN
Platform: UNKNOWN
Classifier: Development Status :: 4 - Beta
Classifier: Intended Audience :: Developers
Classifier: Natural Language :: English
Classifier: License :: OSI Approved :: Apache Software License
Classifier: Operating System :: OS Independent
Classifier: Programming Language :: Python
Classifier: Programming Language :: Python :: 2
Classifier: Programming Language :: Python :: 2.7
Classifier: Topic :: Security
Classifier: Topic :: Software Development :: Libraries :: Python Modules
